{
  "bear_score": 57.117721879451786,
  "allocation": [
    1.0,
    0.0
  ],
  "risk_level": "CAUTION",
  "positions": {
    "NVDA": {
      "shares": 55.0,
      "avg_cost": 182.03
    },
    "LRCX": {
      "shares": 47.0,
      "avg_cost": 209.4409
    },
    "ANET": {
      "shares": 72.0,
      "avg_cost": 137.975
    },
    "MU": {
      "shares": 24.0,
      "avg_cost": 388.535
    },
    "MRVL": {
      "shares": 107.0,
      "avg_cost": 89.05
    },
    "GOOG": {
      "shares": 28.0,
      "avg_cost": 299.65
    },
    "LVS": {
      "shares": 160.0,
      "avg_cost": 54.15
    },
    "NFLX": {
      "shares": 83.0,
      "avg_cost": 98.785
    },
    "META": {
      "shares": 12.0,
      "avg_cost": 646.1749
    },
    "V": {
      "shares": 26.0,
      "avg_cost": 314.81
    },
    "TPR": {
      "shares": 56.0,
      "avg_cost": 145.4
    },
    "PGR": {
      "shares": 39.0,
      "avg_cost": 209.12
    }
  },
  "timestamp": "2026-03-06T15:44:46.804343",
  "last_rebalance": "2026-03-06T15:44:46.804310"
}